libigc/__init__.py
libigc/core.py
libigc/flight_parsing_config.py
libigc/glide.py
libigc/gnss_fix.py
libigc/task.py
libigc/thermal.py
libigc/utils.py
libigc/lib/__init__.py
libigc/lib/dumpers.py
libigc/lib/geo.py
libigc/lib/viterbi.py
libigc-1.1.0.dist-info/LICENSE
libigc-1.1.0.dist-info/METADATA
libigc-1.1.0.dist-info/WHEEL
libigc-1.1.0.dist-info/top_level.txt
libigc-1.1.0.dist-info/RECORD
