Metadata-Version: 2.1
Name: libigc
Version: 1.1.0
Summary: A library for parsing IGC files and extracting thermals
Home-page: https://github.com/surajmandalcell/libigc
Author: Suraj Mandal
Author-email: dev@mandalsuraj.com
Keywords: igc gliding soaring flight-analysis thermal-detection
Classifier: Development Status :: 4 - Beta
Classifier: Intended Audience :: Developers
Classifier: License :: OSI Approved :: MIT License
Classifier: Operating System :: OS Independent
Classifier: Programming Language :: Python :: 3
Classifier: Programming Language :: Python :: 3.6
Classifier: Programming Language :: Python :: 3.7
Classifier: Programming Language :: Python :: 3.8
Classifier: Programming Language :: Python :: 3.9
Classifier: Topic :: Scientific/Engineering :: GIS
Classifier: Topic :: Software Development :: Libraries :: Python Modules
Requires-Python: >=3.6
License-File: LICENSE
Requires-Dist: simplekml>=1.3.1
Requires-Dist: pathlib2>=2.1.0
